opencowork/__init__.py
opencowork_py-0.1.0.dist-info/METADATA
opencowork_py-0.1.0.dist-info/WHEEL
opencowork_py-0.1.0.dist-info/RECORD
