Metadata-Version: 2.4
Name: opencowork-py
Version: 0.1.0
Summary: opencowork
Project-URL: Homepage, https://github.com/SoMarkAI/OpenCowork
Project-URL: Bug-Tracker, https://github.com/SoMarkAI/OpenCowork/issues
Author-email: soulcode <zhangluming@soulcode.cn>
License: MIT
Classifier: License :: OSI Approved :: MIT License
Classifier: Operating System :: OS Independent
Classifier: Programming Language :: Python :: 3
Requires-Python: >=3.8
